.gitignore
AUTHORS.rst
CHANGES.rst
LICENCE.txt
README.rst
setup.cfg
setup.py
docs/Makefile
docs/conf.py
docs/index.rst
sphinx_typesafe/__init__.py
sphinx_typesafe/typesafe.py
sphinx_typesafe.egg-info/PKG-INFO
sphinx_typesafe.egg-info/SOURCES.txt
sphinx_typesafe.egg-info/dependency_links.txt
sphinx_typesafe.egg-info/not-zip-safe
sphinx_typesafe.egg-info/requires.txt
sphinx_typesafe.egg-info/top_level.txt
sphinx_typesafe/tests/__init__.py
sphinx_typesafe/tests/geometry.py
sphinx_typesafe/tests/test_cases.py
sphinx_typesafe/tests/test_classes.py
sphinx_typesafe/tests/test_failures.py
sphinx_typesafe/tests/test_functions.py