Metadata-Version: 1.1
Name: sphinx-typesafe
Version: 0.3
Summary: Type checking @typesafe employing Sphinx docstrings
Home-page: https://github.com/frgomes/sphinx_typesafe
Author: Richard Gomes
Author-email: rgomes.info@gmail.com
License: UNKNOWN
Keywords: type checking docstring
Platform: UNKNOWN
Classifier: Environment :: Web Environment
Classifier: Framework :: Pylons
Classifier: Framework :: Pyramid
Classifier: Intended Audience :: Developers
Classifier: License :: OSI Approved :: Apache Software License
Classifier: Operating System :: OS Independent
Classifier: Programming Language :: Python
Classifier: Programming Language :: Python :: 2.6
Classifier: Programming Language :: Python :: 2.7
Classifier: Topic :: Software Development :: Libraries :: Python Modules
